imagesteg/__init__.py
imagesteg/__main__.py
imagesteg/imagesteg.py
imagesteg/ui/__init__.py
imagesteg/ui/server.py
imagesteg/ui/static/bootstrap.min.css
imagesteg/ui/views/index.tpl
imagesteg-0.3.0.dist-info/LICENSE.txt
imagesteg-0.3.0.dist-info/METADATA
imagesteg-0.3.0.dist-info/WHEEL
imagesteg-0.3.0.dist-info/entry_points.txt
imagesteg-0.3.0.dist-info/RECORD
