Metadata-Version: 2.1
Name: imagesteg
Version: 0.3.0
Summary: A simple image steganalysis (steganography analysis) tool in Python
Home-page: https://github.com/nolze/imagesteg
License: MIT
Author: nolze
Author-email: nolze@int3.net
Requires-Python: >=3.10,<4.0
Classifier: License :: OSI Approved :: MIT License
Classifier: Programming Language :: Python :: 3
Classifier: Programming Language :: Python :: 3.10
Classifier: Programming Language :: Python :: 3.11
Classifier: Programming Language :: Python :: 3.12
Requires-Dist: bitstring (>=4.1.4,<5.0.0)
Requires-Dist: bottle (>=0.12.25,<0.13.0)
Requires-Dist: pillow (>=10.1.0,<11.0.0)
Project-URL: Repository, https://github.com/nolze/imagesteg
